modelify/__init__.py
modelify/cli.py
modelify/helpers.py
modelify/version.py
modelify/app/__init__.py
modelify/app/controller.py
modelify/app/exceptions.py
modelify/app/main.py
modelify/app/model.py
modelify/app/static/bulma.css
modelify/app/static/style.css
modelify/app/templates/custom_ui.html
modelify/app/templates/error.html
modelify/app/templates/form.html
modelify/app/templates/index.html
modelify/app/templates/components/forms/image.html
modelify/app/templates/components/forms/tabular.html
modelify/core/__init__.py
modelify/core/client.py
modelify/core/frameworks.py
modelify/core/inference.py
modelify/inputs/__init__.py
modelify/utils/__init__.py
modelify/utils/constants.py
modelify/utils/credential.py
modelify/utils/inputs.py
modelify/utils/types.py
modelify-0.0.2.8.dist-info/LICENSE.txt
modelify-0.0.2.8.dist-info/METADATA
modelify-0.0.2.8.dist-info/WHEEL
modelify-0.0.2.8.dist-info/entry_points.txt
modelify-0.0.2.8.dist-info/top_level.txt
modelify-0.0.2.8.dist-info/RECORD
