Metadata-Version: 2.1
Name: modelify
Version: 0.0.2.8
Summary: New Version of MLOps Platforms.
Home-page: UNKNOWN
Author: Muzaffer Senkal
Author-email: info@modelify.ai
License: MIT
Keywords: mlops,machine learning,model deployment,deploy model,data science,computer vision
Platform: UNKNOWN
Requires-Dist: numpy
Requires-Dist: pandas
Requires-Dist: cloudpickle
Requires-Dist: python-multipart
Requires-Dist: jinja2
Requires-Dist: Pillow
Requires-Dist: onnxmltools
Requires-Dist: onnxruntime
Requires-Dist: skl2onnx
Requires-Dist: requests-toolbelt
Requires-Dist: tf2onnx
Requires-Dist: pydantic
Requires-Dist: tqdm
Requires-Dist: python-dotenv
Requires-Dist: pyngrok
Requires-Dist: nest-asyncio
Requires-Dist: click
Requires-Dist: uvicorn
Requires-Dist: fastapi
